donkit/ragops_api_gateway_client/client.py
donkit/ragops_api_gateway_client/errors.py
donkit/ragops_api_gateway_client/example.py
donkit/ragops_api_gateway_client/schemas.py
donkit/ragops_api_gateway_client/ws_handler.py
donkit_ragops_api_gateway_client-0.1.6.dist-info/METADATA
donkit_ragops_api_gateway_client-0.1.6.dist-info/WHEEL
donkit_ragops_api_gateway_client-0.1.6.dist-info/RECORD
