Metadata-Version: 2.3
Name: donkit-ragops-api-gateway-client
Version: 0.1.6
Summary: Async HTTP client for interacting with the Donkit ragops-api-gateway
Requires-Python: >=3.12,<3.14
Classifier: Programming Language :: Python :: 3
Classifier: Programming Language :: Python :: 3.12
Classifier: Programming Language :: Python :: 3.13
Requires-Dist: aiohttp (>=3.13,<4.0)
Requires-Dist: pydantic (>=2.12.3,<3.0.0)
Requires-Dist: websockets (>=15.0.1,<16.0.0)
